AUTHORS.rst
CONTRIBUTING.rst
HISTORY.rst
LICENSE
MANIFEST.in
README.rst
setup.cfg
setup.py
mooquant_history/__init__.py
mooquant_history/cli.py
mooquant_history/settings.py
mooquant_history.egg-info/PKG-INFO
mooquant_history.egg-info/SOURCES.txt
mooquant_history.egg-info/dependency_links.txt
mooquant_history.egg-info/entry_points.txt
mooquant_history.egg-info/not-zip-safe
mooquant_history.egg-info/requires.txt
mooquant_history.egg-info/top_level.txt
mooquant_history/formula/__init__.py
mooquant_history/formula/extend.py
mooquant_history/formula/standard.py
mooquant_history/helpers/__init__.py
mooquant_history/helpers/holiday.py
mooquant_history/helpers/symbol.py
mooquant_history/history/__init__.py
mooquant_history/history/api.py
mooquant_history/history/bundle.py
mooquant_history/history/history.py
mooquant_history/history/store.py
mooquant_history/quote/__init__.py
mooquant_history/quote/api.py
mooquant_history/quote/base.py
mooquant_history/quote/helpers.py
tests/__init__.py