Metadata-Version: 1.1
Name: mooquant-history
Version: 0.1.2
Summary: UNKNOWN
Home-page: https://github.com/bopo/mooquant_history
Author: bopowang
Author-email: ibopo@126.com
License: MIT license
Keywords: mooquant_history
Platform: UNKNOWN
Classifier: Development Status :: 2 - Pre-Alpha
Classifier: Intended Audience :: Developers
Classifier: License :: OSI Approved :: MIT License
Classifier: Natural Language :: English
Classifier: Programming Language :: Python :: 3
Classifier: Programming Language :: Python :: 3.3
Classifier: Programming Language :: Python :: 3.4
Classifier: Programming Language :: Python :: 3.5
Classifier: Programming Language :: Python :: 3.6
